scanner/__init__.py
scanner/__main__.py
scanner/ip_scanner.py
scanner/port_scanner.py
scanner/utils.py
lanscanner-1.0.6.dist-info/METADATA
lanscanner-1.0.6.dist-info/WHEEL
lanscanner-1.0.6.dist-info/top_level.txt
lanscanner-1.0.6.dist-info/RECORD
